{
  "ROLLING_WINDOW_DAYS": 180,
  "LAG_DAYS": 0,
  "RB_HIKE_THRESHOLD_CENTS": 1.73,
  "RB_DROP_THRESHOLD_CENTS": -0.76,
  "HO_HIKE_THRESHOLD_CENTS": 1.55,
  "HO_DROP_THRESHOLD_CENTS": -1.38,
  "RB_LEAN_HIKE_CENTS": 0.5,
  "RB_LEAN_DROP_CENTS": -0.5,
  "HO_LEAN_HIKE_CENTS": 0.5,
  "HO_LEAN_DROP_CENTS": -0.5,
  "RB_nymex_daily_std": 8.4188,
  "RB_historical_win_rate": 0.9366,
  "RB_historical_cvar": 3.3175,
  "RB_average_savings": 4.894,
  "RB_window_days": 180,
  "HO_nymex_daily_std": 12.0684,
  "HO_historical_win_rate": 0.8827,
  "HO_historical_cvar": 5.6,
  "HO_average_savings": 7.7191,
  "HO_window_days": 240,
  "RB_high_z_win_rate": 0.7736,
  "RB_high_z_savings": 7.0587,
  "RB_high_z_count": 53,
  "RB_mod_z_win_rate": 0.7937,
  "RB_mod_z_savings": 3.406,
  "RB_mod_z_count": 63,
  "RB_low_z_win_rate": 0.7041,
  "RB_low_z_savings": 1.0417,
  "RB_low_z_count": 267,
  "HO_high_z_win_rate": 0.9394,
  "HO_high_z_savings": 15.9702,
  "HO_high_z_count": 66,
  "HO_mod_z_win_rate": 0.7742,
  "HO_mod_z_savings": 4.2576,
  "HO_mod_z_count": 62,
  "HO_low_z_win_rate": 0.7443,
  "HO_low_z_savings": 1.7902,
  "HO_low_z_count": 219,
  "RB_opt_Hp": 15,
  "RB_opt_Dp": 85,
  "HO_opt_Hp": 15,
  "HO_opt_Dp": 85
}